carunaplusservice/__init__.py
carunaplusservice/api_client.py
carunaplusservice/api_exceptions.py
carunaplusservice/api_response.py
carunaplusservice/carunaplus_session.py
carunaplusservice/cli.py
carunaplusservice/const.py
carunaplusservice/keyring_manager.py
carunaplusservice/price_client.py
carunaplusservice/utils.py
caruna_plus_cli-0.0.6a0.dist-info/LICENSE
caruna_plus_cli-0.0.6a0.dist-info/METADATA
caruna_plus_cli-0.0.6a0.dist-info/WHEEL
caruna_plus_cli-0.0.6a0.dist-info/entry_points.txt
caruna_plus_cli-0.0.6a0.dist-info/top_level.txt
caruna_plus_cli-0.0.6a0.dist-info/RECORD
