Metadata-Version: 2.1
Name: caruna-plus-cli
Version: 0.0.6a0
Summary: Caruna Plus API library and CLI
Home-page: https://github.com/TimotheosOfLifeHill/Caruna-Plus-Client
Author: TimotheosOfLifeHill
Author-email: timo.elovaara@gmail.com
License: MIT license
Classifier: Development Status :: 3 - Alpha
Classifier: Intended Audience :: Developers
Classifier: Intended Audience :: End Users/Desktop
Classifier: License :: OSI Approved :: MIT License
Classifier: Natural Language :: English
Classifier: Programming Language :: Python :: 3
Classifier: Programming Language :: Python :: 3.6
Classifier: Programming Language :: Python :: 3.7
Classifier: Programming Language :: Python :: 3.8
Classifier: Programming Language :: Python :: 3.9
Classifier: Programming Language :: Python :: 3.10
Classifier: Programming Language :: Python :: 3.11
Classifier: Programming Language :: Python :: 3.12
Requires-Python: >=3.6
License-File: LICENSE
Requires-Dist: beautifulsoup4==4.12.3
Requires-Dist: python-dateutil==2.9.0.post0
Requires-Dist: requests>=2.28.1
Requires-Dist: soupsieve==2.5
Requires-Dist: urllib3==1.26.5
Requires-Dist: cachetools>=5.3.3
Requires-Dist: keyring>=23.0.1
